toxsmi/__init__.py
toxsmi/models/__init__.py
toxsmi/models/cnn.py
toxsmi/models/dense.py
toxsmi/models/mca.py
toxsmi/models/rnn.py
toxsmi/utils/__init__.py
toxsmi/utils/hyperparams.py
toxsmi/utils/io.py
toxsmi/utils/layers.py
toxsmi/utils/performance.py
toxsmi/utils/transferlearning.py
toxsmi/utils/utils.py
toxsmi/utils/wrappers.py
toxsmi-1.0.0.data/scripts/eval_tox
toxsmi-1.0.0.data/scripts/train_tox
toxsmi-1.0.0.dist-info/LICENSE
toxsmi-1.0.0.dist-info/METADATA
toxsmi-1.0.0.dist-info/WHEEL
toxsmi-1.0.0.dist-info/top_level.txt
toxsmi-1.0.0.dist-info/RECORD
