Metadata-Version: 2.1
Name: toxsmi
Version: 1.0.0
Summary: PyTorch implementation of toxicity prediction models from SMILES.
Home-page: https://github.com/PaccMann/toxsmi
Author: Jannis Born, Greta Markert, Matteo Manica
Author-email: jab@zurich.ibm.com, greta.markert@gmail.com, drugilsberg@gmail.com
License-File: LICENSE
Requires-Dist: paccmann-predictor
Requires-Dist: numpy >=1.14.3
Requires-Dist: torch
Requires-Dist: Pillow
Requires-Dist: six
Requires-Dist: scikit-learn >=0.21.3
Requires-Dist: brc-pytorch >=0.1.3
Requires-Dist: pytoda >=1.1.2
Requires-Dist: rdkit
